CHANGELOG.txt
LICENSE.txt
MANIFEST.in
README.md
setup.py
test.py
ev3msg/__init__.py
ev3msg.egg-info/PKG-INFO
ev3msg.egg-info/SOURCES.txt
ev3msg.egg-info/dependency_links.txt
ev3msg.egg-info/requires.txt
ev3msg.egg-info/top_level.txt
ev3msg/__modules/ev3mailbox.py