Metadata-Version: 2.1
Name: ev3msg
Version: 0.0.3.7
Summary: A EV3 Messaging Library for Python
Home-page: UNKNOWN
Author: JJTV
License: OSI Approved :: GNU General Public License v3 (GPLv3)
Keywords: ev3,messaging,robotics,communication,protocol,mailbox,py,python
Platform: UNKNOWN
Classifier: Development Status :: 5 - Production/Stable
Classifier: Intended Audience :: Developers
Classifier: License :: OSI Approved :: GNU General Public License v3 (GPLv3)
Classifier: Programming Language :: Python :: 3
License-File: LICENSE.txt
